depman_app/__init__.py
depman_app/depman.py
depman_app-2.1.0.dist-info/entry_points.txt
depman_app-2.1.0.dist-info/WHEEL
depman_app-2.1.0.dist-info/METADATA
depman_app-2.1.0.dist-info/RECORD
