Metadata-Version: 2.4
Name: depman-app
Version: 2.1.0
Summary: DepMan - micro, single-file general-purpose version manager.
Author-email: Maciej Barć <xgqt@xgqt.org>
Requires-Python: >=3.13
Classifier: Environment :: Console
Classifier: Operating System :: POSIX
Classifier: Programming Language :: Python :: 3 :: Only
